{
  "id": "map-20260519185853",
  "name": "6x6 test 1",
  "width": 6,
  "height": 6,
  "tileSize": 72,
  "tiles": [
    {
      "x": 5,
      "y": 5,
      "floor": "normal",
      "spawn": 1,
      "direction": "east"
    },
    {
      "x": 0,
      "y": 0,
      "floor": "normal",
      "checkpoint": 1
    },
    {
      "x": 5,
      "y": 0,
      "floor": "normal",
      "checkpoint": 2
    },
    {
      "x": 0,
      "y": 5,
      "floor": "normal",
      "checkpoint": 3
    },
    {
      "x": 5,
      "y": 3,
      "floor": "normal",
      "conveyor": {
        "type": "normal",
        "direction": "west"
      }
    },
    {
      "x": 4,
      "y": 3,
      "floor": "normal",
      "conveyor": {
        "type": "normal",
        "direction": "west"
      }
    },
    {
      "x": 3,
      "y": 3,
      "floor": "normal",
      "conveyor": {
        "type": "normal",
        "direction": "west"
      }
    },
    {
      "x": 2,
      "y": 3,
      "floor": "pit"
    }
  ]
}